idmtk/.gitignore
idmtk/idmapi/__init__.py
idmtk/idmapi/admin.py
idmtk/idmapi/api.py
idmtk/idmapi/config.py
idmtk/idmapi/exception.py
idmtk/idmapi/models.py
idmtk/idmapi/simulation.py
idmtk/polymer/__init__.py
idmtk/polymer/models.py
idmtk/polymer/polymer.py
idmtk/saxs/.gitignore
idmtk/saxs/RAEDME
idmtk/saxs/__init__.py
idmtk/saxs/calculate_hermans_factor_for_dat.py
idmtk/saxs/edf_2_pic.py
idmtk/saxs/models.py
idmtk-0.3.0.dist-info/METADATA
idmtk-0.3.0.dist-info/WHEEL
idmtk-0.3.0.dist-info/RECORD
