Metadata-Version: 2.3
Name: idmtk
Version: 0.3.0
Summary: 
License: MIT
Author: wolido
Author-email: 270262953@qq.com
Requires-Python: >=3.12,<4.0
Classifier: License :: OSI Approved :: MIT License
Classifier: Programming Language :: Python :: 3
Classifier: Programming Language :: Python :: 3.12
Classifier: Programming Language :: Python :: 3.13
Requires-Dist: fabio (>=2024.9.0,<2025.0.0)
Requires-Dist: matplotlib (>=3.9.3,<4.0.0)
Requires-Dist: numpy (>=2.0.0,<3.0.0)
Requires-Dist: pandas (>=2.2.3,<3.0.0)
Requires-Dist: pydantic (>=2.7.0,<3.0.0)
Requires-Dist: requests (>=2.31.0,<3.0.0)
Requires-Dist: scikit-learn (>=1.5.0,<2.0.0)
